house_prices/__init__.py
house_prices/inference.py
house_prices/preprocess.py
house_prices/train.py
house_prices_jz-0.1.0.dist-info/METADATA
house_prices_jz-0.1.0.dist-info/WHEEL
house_prices_jz-0.1.0.dist-info/top_level.txt
house_prices_jz-0.1.0.dist-info/RECORD
